nearside/file_handler.py
nearside/pkg_info.json
nearside/probe.py
nearside/__init__.py
nearside/cylindrical/structures.py
nearside/cylindrical/__init__.py
nearside/planar/structures.py
nearside/planar/__init__.py
nearside/spherical/low_level.py
nearside/spherical/standard_operations.py
nearside/spherical/structures.py
nearside/spherical/__init__.py
nearside/tests/test_sphere_low_level.py
nearside/tests/test_sphere_standard_operations.py
nearside-0.0.1.dist-info/DESCRIPTION.rst
nearside-0.0.1.dist-info/METADATA
nearside-0.0.1.dist-info/metadata.json
nearside-0.0.1.dist-info/RECORD
nearside-0.0.1.dist-info/top_level.txt
nearside-0.0.1.dist-info/WHEEL
