Metadata-Version: 2.0
Name: nearside
Version: 0.0.1
Summary: A package for processing antenna near-field measurements.
Home-page: https://github.com/rdireen/nearside
Author: Randy Direen
Author-email: nearside@direentech.com
License: GPLv3
Download-URL: https://github.com/rdireen/nearside/tarball/0.0.1
Keywords: near-field antenna measurments planar spherical cylindrical
Platform: UNKNOWN
Classifier: Development Status :: 1 - Planning
Classifier: Intended Audience :: Education
Classifier: Intended Audience :: Science/Research
Classifier: License :: OSI Approved :: GNU General Public License v3 (GPLv3)
Classifier: Operating System :: Microsoft :: Windows :: Windows 7
Classifier: Operating System :: POSIX :: Linux
Classifier: Programming Language :: Python :: 2.7
Classifier: Programming Language :: Python :: 3.3
Classifier: Programming Language :: Python :: 3.4
Classifier: Programming Language :: Python :: Implementation :: CPython
Classifier: Topic :: Scientific/Engineering :: Mathematics
Classifier: Topic :: Scientific/Engineering :: Physics
Requires-Dist: six
Requires-Dist: spherepy
